buscarpy/__init__.py
buscarpy-0.0.2.dist-info/LICENSE
buscarpy-0.0.2.dist-info/METADATA
buscarpy-0.0.2.dist-info/WHEEL
buscarpy-0.0.2.dist-info/top_level.txt
buscarpy-0.0.2.dist-info/RECORD
