Metadata-Version: 2.1
Name: buscarpy
Version: 0.0.2
Summary: Calculate reliable stopping criteria for machine-learning prioritised screening in systematic reviews
Author-email: Max Callaghan <callaghan@mcc-berlin.net>
Project-URL: Homepage, https://github.com/mcallaghan/buscarpy
Project-URL: Bug Tracker, https://github.com/mcallaghan/buscarpy/issues
Classifier: Programming Language :: Python :: 3
Classifier: License :: OSI Approved :: MIT License
Classifier: Operating System :: OS Independent
Requires-Python: >=3.7
License-File: LICENSE
Requires-Dist: matplotlib>=3.5.0
Requires-Dist: scipy>=1.7.2
Requires-Dist: numpy>=1.17.0
Requires-Dist: pandas>=2.1.1
